{
  "schema": "companion.v1",
  "naamgever": {
    "naam": "Eddy Merckx",
    "discipline": {
      "nl": "Wielrenner · °1945",
      "fr": "Coureur cycliste · °1945",
      "en": "Racing cyclist · b. 1945"
    },
    "omschrijving": {
      "nl": "Belgische wielrenner, door velen beschouwd als de beste aller tijden.",
      "fr": "Coureur cycliste belge, considéré par beaucoup comme le meilleur de tous les temps.",
      "en": "Belgian cyclist, regarded by many as the greatest of all time."
    },
    "weetjes": [
      {
        "nl": "Eddy Merckx won elf Grote Rondes: vijf Tours, vijf Giro’s en één Vuelta.",
        "fr": "Eddy Merckx a remporté onze Grands Tours : cinq Tours, cinq Giros et une Vuelta.",
        "en": "Eddy Merckx won eleven Grand Tours: five Tours, five Giros and one Vuelta."
      },
      {
        "nl": "Merckx won negentien Monumenten. Dat is nog altijd het record.",
        "fr": "Merckx a remporté dix-neuf Monuments. C’est toujours le record.",
        "en": "Merckx won nineteen Monuments. That is still the record."
      },
      {
        "nl": "Milaan-San Remo won Merckx zeven keer.",
        "fr": "Merckx a remporté Milan-San Remo à sept reprises.",
        "en": "Merckx won Milan-San Remo seven times."
      },
      {
        "nl": "Merckx won tijdens zijn carrière alle vijf de wielerMonumenten.",
        "fr": "Au cours de sa carrière, Merckx a remporté les cinq Monuments du cyclisme.",
        "en": "During his career, Merckx won all five of cycling’s Monuments."
      },
      {
        "nl": "In 1974 won Merckx de Giro, de Tour én het wereldkampioenschap in hetzelfde jaar.",
        "fr": "En 1974, Merckx remporte le Giro, le Tour et le championnat du monde la même année.",
        "en": "In 1974, Merckx won the Giro, the Tour and the World Championship in the same year."
      },
      {
        "nl": "Merckx was in 1974 de eerste man die de beroemde Triple Crown van Giro, Tour en WK pakte.",
        "fr": "En 1974, Merckx devient le premier homme à réaliser la célèbre Triple Couronne : Giro, Tour et Mondial.",
        "en": "In 1974, Merckx became the first man to achieve the famous Triple Crown: Giro, Tour and World Championship."
      },
      {
        "nl": "Merckx droeg 111 dagen de gele trui in de Tour. Niemand deed dat vaker.",
        "fr": "Merckx a porté le maillot jaune pendant 111 jours sur le Tour. Personne ne l’a fait plus souvent.",
        "en": "Merckx wore the Tour’s yellow jersey for 111 days. No one has done it more often."
      },
      {
        "nl": "Bij zijn eerste Tourdeelname in 1969 won Merckx meteen het eindklassement.",
        "fr": "Pour sa première participation au Tour en 1969, Merckx remporte directement le classement général.",
        "en": "In his first Tour de France in 1969, Merckx immediately won the overall classification."
      },
      {
        "nl": "In de Tour van 1969 won Merckx het algemeen klassement, het puntenklassement én het bergklassement.",
        "fr": "Lors du Tour 1969, Merckx remporte le classement général, le classement par points et le classement de la montagne.",
        "en": "At the 1969 Tour, Merckx won the general, points and mountains classifications."
      },
      {
        "nl": "Merckx nam in 1964 als 19-jarige amateur deel aan de Olympische Spelen van Tokio.",
        "fr": "En 1964, Merckx participe aux Jeux olympiques de Tokyo comme amateur de 19 ans.",
        "en": "In 1964, Merckx competed at the Tokyo Olympics as a 19-year-old amateur."
      },
      {
        "nl": "Merckx won 64 ritten in de drie Grote Rondes samen.",
        "fr": "Merckx a remporté 64 étapes dans l’ensemble des trois Grands Tours.",
        "en": "Merckx won 64 stages across the three Grand Tours."
      },
      {
        "nl": "Alleen al in de Tour de France won Merckx 34 ritten.",
        "fr": "Rien que sur le Tour de France, Merckx a remporté 34 étapes.",
        "en": "In the Tour de France alone, Merckx won 34 stages."
      },
      {
        "nl": "Merckx won 24 ritten in de Giro en zes in de Vuelta.",
        "fr": "Merckx a remporté 24 étapes sur le Giro et six sur la Vuelta.",
        "en": "Merckx won 24 Giro stages and six Vuelta stages."
      },
      {
        "nl": "Merckx werd drie keer wereldkampioen op de weg.",
        "fr": "Merckx a été trois fois champion du monde sur route.",
        "en": "Merckx became road world champion three times."
      },
      {
        "nl": "Zijn bijnaam De Kannibaal kreeg Merckx omdat hij bleef aanvallen en winnen, zelfs wanneer hij al domineerde.",
        "fr": "Merckx a reçu le surnom de Cannibale parce qu’il continuait à attaquer et à gagner, même lorsqu’il dominait déjà.",
        "en": "Merckx earned the nickname The Cannibal because he kept attacking and winning, even when he was already dominant."
      }
    ]
  },
  "bronnen": [
    "https://www.olympics.com/en/athletes/eddy-merckx",
    "https://www.letour.fr/es/datos/datos-del-dia-etapa-21",
    "https://www.uci.org/article/uci-road-and-para-cycling-road-world-champs-pogacars-closing-masterclass/fvr4cXIs9lVch7ZQ7PGCa",
    "https://www.procyclingstats.com/statistics/grandtours/most-wins",
    "https://www.procyclingstats.com/statistics/grandtours/most-stage-wins"
  ]
}